{
  "url": "https://grant.codes/websites",
  "requestedUrl": "https://grant.codes/websites",
  "timestamp": 1619484239049,
  "ranks": {
    "hundos": 9,
    "performance": 9,
    "accessibility": 10,
    "cumulative": 9
  },
  "lighthouse": {
    "version": "6.5.0",
    "performance": 0.93,
    "accessibility": 0.75,
    "bestPractices": 1,
    "seo": 0.86,
    "total": 354
  },
  "firstContentfulPaint": 1976.571,
  "speedIndex": 1976.571,
  "largestContentfulPaint": 2726.571,
  "totalBlockingTime": 219,
  "cumulativeLayoutShift": 0.16110571289062503,
  "timeToInteractive": 2572.571,
  "maxPotentialFirstInputDelay": 197,
  "timeToFirstByte": 15.723999999999997,
  "weight": {
    "summary": "53 requests • 763 KiB",
    "total": 780854,
    "image": 320352,
    "imageCount": 9,
    "script": 119495,
    "scriptCount": 11,
    "document": 23172,
    "font": 44402,
    "fontCount": 2,
    "stylesheet": 10290,
    "stylesheetCount": 2,
    "thirdParty": 0,
    "thirdPartyCount": 0
  },
  "run": {
    "number": 2,
    "total": 3
  },
  "axe": {
    "passes": 231,
    "violations": 25
  }
}