{
  "url": "https://kinsta.com/knowledgebase/dns_probe_finished_nxdomain/",
  "requestedUrl": "https://kinsta.com/knowledgebase/dns_probe_finished_nxdomain/",
  "timestamp": 1607386938182,
  "ranks": {
    "hundos": 3,
    "performance": 4,
    "accessibility": 1,
    "cumulative": 3
  },
  "lighthouse": {
    "version": "6.5.0",
    "performance": 0.5,
    "accessibility": 0.86,
    "bestPractices": 0.8,
    "seo": 1,
    "total": 316
  },
  "firstContentfulPaint": 2336.843,
  "speedIndex": 6229.1643963602555,
  "largestContentfulPaint": 3160.0029999999997,
  "totalBlockingTime": 1025.5,
  "cumulativeLayoutShift": 0,
  "timeToInteractive": 12423.958999999999,
  "maxPotentialFirstInputDelay": 352,
  "timeToFirstByte": 157.77499999999998,
  "weight": {
    "summary": "72 requests • 2,079 KiB",
    "total": 2129302,
    "image": 966761,
    "imageCount": 10,
    "script": 892110,
    "scriptCount": 39,
    "document": 38908,
    "font": 135191,
    "fontCount": 6,
    "stylesheet": 82088,
    "stylesheetCount": 2,
    "thirdParty": 1081585,
    "thirdPartyCount": 46
  },
  "axe": {
    "passes": 1358,
    "violations": 205
  }
}