{
  "url": "https://kinsta.com/knowledgebase/dns_probe_finished_nxdomain/",
  "requestedUrl": "https://kinsta.com/knowledgebase/dns_probe_finished_nxdomain/",
  "timestamp": 1602440760136,
  "ranks": {
    "hundos": 6,
    "performance": 7,
    "accessibility": 1,
    "cumulative": 6
  },
  "lighthouse": {
    "version": "6.4.1",
    "performance": 0.31,
    "accessibility": 0.86,
    "bestPractices": 0.71,
    "seo": 1,
    "total": 288
  },
  "firstContentfulPaint": 2178.733,
  "speedIndex": 5541.449849410988,
  "largestContentfulPaint": 7118.493,
  "totalBlockingTime": 1462.4999999999977,
  "cumulativeLayoutShift": 0.0538125,
  "timeToInteractive": 16515.5355,
  "maxPotentialFirstInputDelay": 380,
  "timeToFirstByte": 128.327,
  "weight": {
    "summary": "114 requests • 2,337 KiB",
    "total": 2393003,
    "image": 1054833,
    "imageCount": 28,
    "script": 1074013,
    "scriptCount": 54,
    "document": 42341,
    "font": 103103,
    "fontCount": 5,
    "stylesheet": 82663,
    "stylesheetCount": 2,
    "thirdParty": 1299205,
    "thirdPartyCount": 85
  },
  "axe": {
    "passes": 1623,
    "violations": 213
  }
}