{
  "url": "https://kinsta.com/ebooks/wordpress/manage-multiple-wordpress-sites/",
  "requestedUrl": "https://kinsta.com/ebooks/wordpress/manage-multiple-wordpress-sites/",
  "timestamp": 1611685411880,
  "ranks": {
    "hundos": 4,
    "performance": 4,
    "accessibility": 6,
    "cumulative": 4
  },
  "lighthouse": {
    "version": "6.5.0",
    "performance": 0.37,
    "accessibility": 0.77,
    "bestPractices": 0.8,
    "seo": 0.93,
    "total": 287
  },
  "firstContentfulPaint": 2504.3440000000005,
  "speedIndex": 6626.20951336083,
  "largestContentfulPaint": 3797.8140000000017,
  "totalBlockingTime": 2150.6419999999957,
  "cumulativeLayoutShift": 0.18699871656629774,
  "timeToInteractive": 17139.8415,
  "maxPotentialFirstInputDelay": 474,
  "timeToFirstByte": 129.994,
  "weight": {
    "summary": "109 requests • 1,931 KiB",
    "total": 1976981,
    "image": 393249,
    "imageCount": 21,
    "script": 1271639,
    "scriptCount": 49,
    "document": 45133,
    "font": 146282,
    "fontCount": 7,
    "stylesheet": 86947,
    "stylesheetCount": 3,
    "thirdParty": 962103,
    "thirdPartyCount": 76
  },
  "run": {
    "number": 2,
    "total": 3
  },
  "axe": {
    "passes": 718,
    "violations": 31
  }
}