{
  "url": "https://kinsta.com/",
  "requestedUrl": "https://kinsta.com/",
  "timestamp": 1614449751867,
  "ranks": {
    "hundos": 1,
    "performance": 2,
    "accessibility": 3,
    "cumulative": 1
  },
  "lighthouse": {
    "version": "6.5.0",
    "performance": 0.45,
    "accessibility": 0.81,
    "bestPractices": 0.8,
    "seo": 0.93,
    "total": 299
  },
  "firstContentfulPaint": 2463.205,
  "speedIndex": 5998.277723160521,
  "largestContentfulPaint": 3085.3369999999995,
  "totalBlockingTime": 2724.4999999999977,
  "cumulativeLayoutShift": 0,
  "timeToInteractive": 17155.765999999996,
  "maxPotentialFirstInputDelay": 841,
  "timeToFirstByte": 134.60299999999998,
  "weight": {
    "summary": "136 requests • 1,565 KiB",
    "total": 1602823,
    "image": 214502,
    "imageCount": 50,
    "script": 1046585,
    "scriptCount": 48,
    "document": 36079,
    "font": 135108,
    "fontCount": 6,
    "stylesheet": 83929,
    "stylesheetCount": 2,
    "thirdParty": 691162,
    "thirdPartyCount": 69
  },
  "run": {
    "number": 1,
    "total": 3
  },
  "axe": {
    "passes": 1889,
    "violations": 88
  }
}