{
  "url": "https://grant.codes/collections",
  "requestedUrl": "https://grant.codes/collections",
  "timestamp": 1610586202396,
  "ranks": {
    "hundos": 6,
    "performance": 8,
    "accessibility": 4,
    "cumulative": 6
  },
  "lighthouse": {
    "version": "6.5.0",
    "performance": 0.86,
    "accessibility": 0.79,
    "bestPractices": 0.93,
    "seo": 0.93,
    "total": 351
  },
  "firstContentfulPaint": 2721.2200000000003,
  "speedIndex": 2721.2200000000003,
  "largestContentfulPaint": 2871.2200000000003,
  "totalBlockingTime": 377.9999999999993,
  "cumulativeLayoutShift": 0.019987413194444446,
  "timeToInteractive": 3482.22,
  "maxPotentialFirstInputDelay": 706.9999999999995,
  "timeToFirstByte": 22.659,
  "weight": {
    "summary": "132 requests • 1,410 KiB",
    "total": 1443827,
    "image": 907937,
    "imageCount": 76,
    "script": 350446,
    "scriptCount": 16,
    "document": 44067,
    "font": 44403,
    "fontCount": 2,
    "stylesheet": 11391,
    "stylesheetCount": 2,
    "thirdParty": 896620,
    "thirdPartyCount": 75
  },
  "run": {
    "number": 3,
    "total": 3
  },
  "axe": {
    "passes": 1623,
    "violations": 245
  }
}