{
  "url": "https://grant.codes/2020/08/09/100days-conclusion",
  "requestedUrl": "https://grant.codes/2020/08/09/100days-conclusion",
  "timestamp": 1601144403191,
  "ranks": {
    "hundos": 6,
    "performance": 4,
    "accessibility": 8,
    "cumulative": 6
  },
  "lighthouse": {
    "version": "6.3.0",
    "performance": 0.96,
    "accessibility": 0.77,
    "bestPractices": 1,
    "seo": 0.92,
    "total": 365
  },
  "firstContentfulPaint": 2257.65,
  "speedIndex": 2257.65,
  "largestContentfulPaint": 2407.65,
  "totalBlockingTime": 72.5,
  "cumulativeLayoutShift": 0.00209564208984375,
  "timeToInteractive": 2977.65,
  "maxPotentialFirstInputDelay": 195,
  "timeToFirstByte": 8.996000000000002,
  "weight": {
    "summary": "40 requests • 484 KiB",
    "total": 495278,
    "image": 11321,
    "imageCount": 1,
    "script": 231561,
    "scriptCount": 14,
    "document": 24823,
    "font": 44402,
    "fontCount": 2,
    "stylesheet": 10926,
    "stylesheetCount": 2,
    "thirdParty": 0,
    "thirdPartyCount": 0
  },
  "axe": {
    "passes": 236,
    "violations": 31
  }
}